{
  "last_updated": "2025-11-30T19:49:29.799081",
  "matches_count": 16,
  "data": [
    {
      "home": {
        "name": "Crystal Palace",
        "logo_url": "https://football-logos.cc/logos/england/256x256/crystal-palace.53067b96.png"
      },
      "away": {
        "name": "Manchester United",
        "logo_url": "https://football-logos.cc/logos/england/256x256/manchester-united.7ab9d343.png"
      },
      "stream_urls": [
        "https://ghb.stad90.com/UpFiles/2025/11/30/51/309185/0.m3u8?token=30112025214857|Referer=https://hoofootay4.spotlightmoment.com/",
        "https://ghb.stad90.com/UpFiles/2025/11/30/51/309185/0.m3u8?token=30112025214859|Referer=https://hoofootay4.spotlightmoment.com/"
      ],
      "date": "Today",
      "league": "Premier League"
    },
    {
      "home": {
        "name": "West Ham",
        "logo_url": "https://football-logos.cc/logos/china/256x256/qingdao-west-coast.b27c8f29.png"
      },
      "away": {
        "name": "Liverpool",
        "logo_url": ""
      },
      "stream_urls": [
        "https://ghb.stad90.com/UpFiles/2025/11/30/51/309208/0.m3u8?token=30112025214900|Referer=https://hoofootay4.spotlightmoment.com/",
        "https://ghb.stad90.com/UpFiles/2025/11/30/51/309208/0.m3u8?token=30112025214901|Referer=https://hoofootay4.spotlightmoment.com/"
      ],
      "date": "Today",
      "league": "Premier League"
    },
    {
      "home": {
        "name": "Chelsea",
        "logo_url": ""
      },
      "away": {
        "name": "Arsenal",
        "logo_url": "https://football-logos.cc/logos/belarus/256x256/arsenal-dzerzhinsk.69bc46d7.png"
      },
      "stream_urls": [
        "https://ghb.stad90.com/UpFiles/2025/11/30/51/309219/0.m3u8?token=30112025214902|Referer=https://hoofootay4.spotlightmoment.com/",
        "https://ghb.stad90.com/UpFiles/2025/11/30/51/309219/0.m3u8?token=30112025214903|Referer=https://hoofootay4.spotlightmoment.com/"
      ],
      "date": "Today",
      "league": "Premier League"
    },
    {
      "home": {
        "name": "Aston Villa",
        "logo_url": "https://football-logos.cc/logos/england/256x256/aston-villa.07a2646c.png"
      },
      "away": {
        "name": "Wolves",
        "logo_url": ""
      },
      "stream_urls": [
        "https://ghb.stad90.com/UpFiles/2025/11/30/51/309211/0.m3u8?token=30112025214904|Referer=https://hoofootay4.spotlightmoment.com/",
        "https://ghb.stad90.com/UpFiles/2025/11/30/51/309211/0.m3u8?token=30112025214905|Referer=https://hoofootay4.spotlightmoment.com/"
      ],
      "date": "Today",
      "league": "Premier League"
    },
    {
      "home": {
        "name": "Nottingham",
        "logo_url": "https://football-logos.cc/logos/england/256x256/nottingham-forest.43b53a26.png"
      },
      "away": {
        "name": "Brighton",
        "logo_url": ""
      },
      "stream_urls": [
        "https://ghb.stad90.com/UpFiles/2025/11/30/51/309224/0.m3u8?token=30112025214906|Referer=https://hoofootay4.spotlightmoment.com/",
        "https://ghb.stad90.com/UpFiles/2025/11/30/51/309224/0.m3u8?token=30112025214907|Referer=https://hoofootay4.spotlightmoment.com/"
      ],
      "date": "Today",
      "league": "Premier League"
    },
    {
      "home": {
        "name": "Pisa",
        "logo_url": ""
      },
      "away": {
        "name": "Inter",
        "logo_url": "https://football-logos.cc/logos/andorra/256x256/inter-escaldes.28803240.png"
      },
      "stream_urls": [
        "https://ghb.stad90.com/UpFiles/2025/11/30/51/309197/0.m3u8?token=30112025214908|Referer=https://hoofootay4.spotlightmoment.com/",
        "https://ghb.stad90.com/UpFiles/2025/11/30/51/309197/0.m3u8?token=30112025214909|Referer=https://hoofootay4.spotlightmoment.com/"
      ],
      "date": "Today",
      "league": "Serie A"
    },
    {
      "home": {
        "name": "Hamburg",
        "logo_url": ""
      },
      "away": {
        "name": "Stuttgart",
        "logo_url": ""
      },
      "stream_urls": [
        "https://ghb.stad90.com/UpFiles/2025/11/30/51/309206/0.m3u8?token=30112025214910|Referer=https://hoofootay4.spotlightmoment.com/",
        "https://ghb.stad90.com/UpFiles/2025/11/30/51/309206/0.m3u8?token=30112025214910|Referer=https://hoofootay4.spotlightmoment.com/"
      ],
      "date": "Today",
      "league": "BundesLiga"
    },
    {
      "home": {
        "name": "Real Sociedad",
        "logo_url": "https://football-logos.cc/logos/spain/256x256/real-madrid.5ce15611.png"
      },
      "away": {
        "name": "Villarreal",
        "logo_url": ""
      },
      "stream_urls": [
        "https://ghb.stad90.com/UpFiles/2025/11/30/51/309187/0.m3u8?token=30112025214911|Referer=https://hoofootay4.spotlightmoment.com/",
        "https://ghb.stad90.com/UpFiles/2025/11/30/51/309187/0.m3u8?token=30112025214912|Referer=https://hoofootay4.spotlightmoment.com/"
      ],
      "date": "Today",
      "league": "La Liga"
    },
    {
      "home": {
        "name": "Sevilla",
        "logo_url": ""
      },
      "away": {
        "name": "Betis",
        "logo_url": ""
      },
      "stream_urls": [
        "https://ghb.stad90.com/UpFiles/2025/11/30/51/309215/0.m3u8?token=30112025214913|Referer=https://hoofootay4.spotlightmoment.com/",
        "https://ghb.stad90.com/UpFiles/2025/11/30/51/309215/0.m3u8?token=30112025214914|Referer=https://hoofootay4.spotlightmoment.com/"
      ],
      "date": "Today",
      "league": "La Liga"
    },
    {
      "home": {
        "name": "Strasbourg",
        "logo_url": "https://football-logos.cc/logos/france/256x256/rc-strasbourg-alsace.d91bd009.png"
      },
      "away": {
        "name": "Brest",
        "logo_url": ""
      },
      "stream_urls": [
        "https://ghb.stad90.com/UpFiles/2025/11/30/51/309203/0.m3u8?token=30112025214915|Referer=https://hoofootay4.spotlightmoment.com/",
        "https://ghb.stad90.com/UpFiles/2025/11/30/51/309203/0.m3u8?token=30112025214917|Referer=https://hoofootay4.spotlightmoment.com/"
      ],
      "date": "Today",
      "league": "Ligue 1"
    },
    {
      "home": {
        "name": "Angers",
        "logo_url": ""
      },
      "away": {
        "name": "Lens",
        "logo_url": ""
      },
      "stream_urls": [
        "https://ghb.stad90.com/UpFiles/2025/11/30/51/309221/0.m3u8?token=30112025214918|Referer=https://hoofootay4.spotlightmoment.com/",
        "https://ghb.stad90.com/UpFiles/2025/11/30/51/309221/0.m3u8?token=30112025214919|Referer=https://hoofootay4.spotlightmoment.com/"
      ],
      "date": "Today",
      "league": "Ligue 1"
    },
    {
      "home": {
        "name": "Frankfurt",
        "logo_url": ""
      },
      "away": {
        "name": "Wolfsburg",
        "logo_url": ""
      },
      "stream_urls": [
        "https://ghb.stad90.com/UpFiles/2025/11/30/51/309222/0.m3u8?token=30112025214920|Referer=https://hoofootay4.spotlightmoment.com/",
        "https://ghb.stad90.com/UpFiles/2025/11/30/51/309222/0.m3u8?token=30112025214921|Referer=https://hoofootay4.spotlightmoment.com/"
      ],
      "date": "Today",
      "league": "BundesLiga"
    },
    {
      "home": {
        "name": "Atalanta",
        "logo_url": ""
      },
      "away": {
        "name": "Fiorentina",
        "logo_url": ""
      },
      "stream_urls": [
        "https://ghb.stad90.com/UpFiles/2025/11/30/51/309225/0.m3u8?token=30112025214922|Referer=https://hoofootay4.spotlightmoment.com/",
        "https://ghb.stad90.com/UpFiles/2025/11/30/51/309225/0.m3u8?token=30112025214923|Referer=https://hoofootay4.spotlightmoment.com/"
      ],
      "date": "Today",
      "league": "Serie A"
    },
    {
      "home": {
        "name": "Lecce",
        "logo_url": ""
      },
      "away": {
        "name": "Torino",
        "logo_url": ""
      },
      "stream_urls": [
        "https://ghb.stad90.com/UpFiles/2025/11/30/51/309178/0.m3u8?token=30112025214924|Referer=https://hoofootay4.spotlightmoment.com/",
        "https://ghb.stad90.com/UpFiles/2025/11/30/51/309178/0.m3u8?token=30112025214925|Referer=https://hoofootay4.spotlightmoment.com/"
      ],
      "date": "Today",
      "league": "Serie A"
    },
    {
      "home": {
        "name": "PSV",
        "logo_url": ""
      },
      "away": {
        "name": "Volendam",
        "logo_url": ""
      },
      "stream_urls": [
        "https://ghb.stad90.com/UpFiles/2025/11/30/51/309180/0.m3u8?token=30112025214926|Referer=https://hoofootay4.spotlightmoment.com/",
        "https://ghb.stad90.com/UpFiles/2025/11/30/51/309180/0.m3u8?token=30112025214927|Referer=https://hoofootay4.spotlightmoment.com/"
      ],
      "date": "Today",
      "league": "Eredivisie"
    },
    {
      "home": {
        "name": "Manchester City",
        "logo_url": "https://football-logos.cc/logos/england/256x256/manchester-united.7ab9d343.png"
      },
      "away": {
        "name": "Leeds",
        "logo_url": "https://football-logos.cc/logos/england/256x256/leeds-united.26dba8f5.png"
      },
      "stream_urls": [
        "https://ghb.stad90.com/UpFiles/2025/11/29/51/309148/0.m3u8?token=30112025214928|Referer=https://hoofootay4.spotlightmoment.com/",
        "https://ghb.stad90.com/UpFiles/2025/11/29/51/309148/0.m3u8?token=30112025214929|Referer=https://hoofootay4.spotlightmoment.com/"
      ],
      "date": "Yesterday",
      "league": "Premier League"
    }
  ]
}